{
  "project_info": {
    "project_number": "798121423440",
    "firebase_url": "https://billient-ff8da.firebaseio.com",
    "project_id": "billient-ff8da",
    "storage_bucket": "billient-ff8da.appspot.com"
  },
  "client": [
    {
      "client_info": {
        "mobilesdk_app_id": "1:798121423440:android:c8a510d7a59c8c16",
        "android_client_info": {
          "package_name": "com.gifskey.testonesignal"
        }
      },
      "oauth_client": [
        {
          "client_id": "798121423440-2qvqhqroq29jsvc4nvrvb03mp9lcfli7.apps.googleusercontent.com",
          "client_type": 3
        }
      ],
      "api_key": [
        {
          "current_key": "AIzaSyBI_8JMJQ8jEbCxFHk1IcLB3Cl-O9mO5Wo"
        }
      ],
      "services": {
        "appinvite_service": {
          "other_platform_oauth_client": [
            {
              "client_id": "798121423440-kiat5j89fi7dfb5i0qsnnoogjfheag71.apps.googleusercontent.com",
              "client_type": 3
            },
            {
              "client_id": "798121423440-v139ggmqbrcb6mmotk1vp6a2fjlfn7nt.apps.googleusercontent.com",
              "client_type": 2,
              "ios_info": {
                "bundle_id": "com.saikrishna.anony"
              }
            }
          ]
        }
      }
    },
    {
      "client_info": {
        "mobilesdk_app_id": "1:798121423440:android:71dcfa22498aeb96",
        "android_client_info": {
          "package_name": "com.saikrishna.firebaseauth"
        }
      },
      "oauth_client": [
        {
          "client_id": "798121423440-0ve2sbjhtjsch0cpfspmq6ms8cttjcbl.apps.googleusercontent.com",
          "client_type": 1,
          "android_info": {
            "package_name": "com.saikrishna.firebaseauth",
            "certificate_hash": "17d47d00458eba7fcc1e8c48c414e2667f930271"
          }
        },
        {
          "client_id": "798121423440-2qvqhqroq29jsvc4nvrvb03mp9lcfli7.apps.googleusercontent.com",
          "client_type": 3
        }
      ],
      "api_key": [
        {
          "current_key": "AIzaSyBI_8JMJQ8jEbCxFHk1IcLB3Cl-O9mO5Wo"
        }
      ],
      "services": {
        "appinvite_service": {
          "other_platform_oauth_client": [
            {
              "client_id": "798121423440-kiat5j89fi7dfb5i0qsnnoogjfheag71.apps.googleusercontent.com",
              "client_type": 3
            },
            {
              "client_id": "798121423440-v139ggmqbrcb6mmotk1vp6a2fjlfn7nt.apps.googleusercontent.com",
              "client_type": 2,
              "ios_info": {
                "bundle_id": "com.saikrishna.anony"
              }
            }
          ]
        }
      }
    },
    {
      "client_info": {
        "mobilesdk_app_id": "1:798121423440:android:8c3052eda57adf47",
        "android_client_info": {
          "package_name": "com.saikrishna.gifskeykeyboard"
        }
      },
      "oauth_client": [
        {
          "client_id": "798121423440-9v0usuh54ctse4madvjfvg0vsv5rhcce.apps.googleusercontent.com",
          "client_type": 1,
          "android_info": {
            "package_name": "com.saikrishna.gifskeykeyboard",
            "certificate_hash": "17d47d00458eba7fcc1e8c48c414e2667f930271"
          }
        },
        {
          "client_id": "798121423440-2qvqhqroq29jsvc4nvrvb03mp9lcfli7.apps.googleusercontent.com",
          "client_type": 3
        }
      ],
      "api_key": [
        {
          "current_key": "AIzaSyBI_8JMJQ8jEbCxFHk1IcLB3Cl-O9mO5Wo"
        }
      ],
      "services": {
        "appinvite_service": {
          "other_platform_oauth_client": [
            {
              "client_id": "798121423440-kiat5j89fi7dfb5i0qsnnoogjfheag71.apps.googleusercontent.com",
              "client_type": 3
            },
            {
              "client_id": "798121423440-v139ggmqbrcb6mmotk1vp6a2fjlfn7nt.apps.googleusercontent.com",
              "client_type": 2,
              "ios_info": {
                "bundle_id": "com.saikrishna.anony"
              }
            }
          ]
        }
      }
    },
    {
      "client_info": {
        "mobilesdk_app_id": "1:798121423440:android:b329887875b8cbd78b9755",
        "android_client_info": {
          "package_name": "com.saikrishna.mocktrade"
        }
      },
      "oauth_client": [
        {
          "client_id": "798121423440-2qvqhqroq29jsvc4nvrvb03mp9lcfli7.apps.googleusercontent.com",
          "client_type": 3
        }
      ],
      "api_key": [
        {
          "current_key": "AIzaSyBI_8JMJQ8jEbCxFHk1IcLB3Cl-O9mO5Wo"
        }
      ],
      "services": {
        "appinvite_service": {
          "other_platform_oauth_client": [
            {
              "client_id": "798121423440-kiat5j89fi7dfb5i0qsnnoogjfheag71.apps.googleusercontent.com",
              "client_type": 3
            },
            {
              "client_id": "798121423440-v139ggmqbrcb6mmotk1vp6a2fjlfn7nt.apps.googleusercontent.com",
              "client_type": 2,
              "ios_info": {
                "bundle_id": "com.saikrishna.anony"
              }
            }
          ]
        }
      }
    },
    {
      "client_info": {
        "mobilesdk_app_id": "1:798121423440:android:ef1430c656e727e9",
        "android_client_info": {
          "package_name": "com.saikrishna.succour"
        }
      },
      "oauth_client": [
        {
          "client_id": "798121423440-3srb8dp1jfsf3s8bdqu5fdesng093ags.apps.googleusercontent.com",
          "client_type": 1,
          "android_info": {
            "package_name": "com.saikrishna.succour",
            "certificate_hash": "52b55cffed24ec353f113baff4234c8f043c9664"
          }
        },
        {
          "client_id": "798121423440-2qvqhqroq29jsvc4nvrvb03mp9lcfli7.apps.googleusercontent.com",
          "client_type": 3
        }
      ],
      "api_key": [
        {
          "current_key": "AIzaSyBI_8JMJQ8jEbCxFHk1IcLB3Cl-O9mO5Wo"
        }
      ],
      "services": {
        "appinvite_service": {
          "other_platform_oauth_client": [
            {
              "client_id": "798121423440-kiat5j89fi7dfb5i0qsnnoogjfheag71.apps.googleusercontent.com",
              "client_type": 3
            },
            {
              "client_id": "798121423440-v139ggmqbrcb6mmotk1vp6a2fjlfn7nt.apps.googleusercontent.com",
              "client_type": 2,
              "ios_info": {
                "bundle_id": "com.saikrishna.anony"
              }
            }
          ]
        }
      }
    }
  ],
  "configuration_version": "1"
}